{
    "k": 15,
    "inertia_score": -101944.828125,
    "silhouette_score": 0.15900467336177826,
    "cluster_counts": [
        76,
        39,
        41,
        28,
        40,
        27,
        33,
        65,
        66,
        26,
        57,
        47,
        18,
        71,
        47
    ],
    "centroids": [
        "index19_frame_004",
        "index57_frame_013",
        "Screenshot (422)",
        "Screenshot (2)",
        "index102_frame_017",
        "index62_frame_001",
        "index88_frame_009",
        "index2_frame_016",
        "index8_frame_021",
        "index82_frame_016",
        "Alto 40",
        "index20_frame_017",
        "index31_frame_013",
        "index100_frame_009",
        "index104_frame_011"
    ],
    "samples": [
        [
            "index19_frame_012",
            "index19_frame_005",
            "index66_frame_004",
            "index66_frame_008",
            "index66_frame_014",
            "index19_frame_025",
            "index19_frame_028",
            "index107_frame_006",
            "index66_frame_002",
            "index19_frame_011",
            "index59_frame_006",
            "index59_frame_009",
            "index107_frame_016",
            "index59_frame_013",
            "index108_frame_003",
            "index71_frame_006",
            "index107_frame_014",
            "index9_frame_016",
            "index59_frame_010"
        ],
        [
            "index57_frame_009",
            "index57_frame_015",
            "index57_frame_020",
            "index74_frame_004",
            "index74_frame_011",
            "index57_frame_012",
            "index74_frame_010",
            "index74_frame_006",
            "index57_frame_017",
            "index57_frame_010",
            "index74_frame_012",
            "index74_frame_019",
            "index74_frame_014",
            "index57_frame_005",
            "index74_frame_008",
            "index57_frame_002",
            "index57_frame_014",
            "index74_frame_017",
            "index74_frame_009"
        ],
        [
            "Screenshot (428)",
            "Screenshot (409)",
            "Screenshot (419)",
            "Screenshot (414)",
            "DataSetVari 21",
            "Screenshot (453)",
            "Screenshot (408)",
            "Screenshot (417)",
            "Screenshot (410)",
            "Screenshot (461)",
            "Screenshot (455)",
            "Screenshot (442)",
            "Screenshot (440)",
            "index106_frame_002",
            "index106_frame_004",
            "DataSetVari 22",
            "index106_frame_007",
            "index106_frame_001",
            "index106_frame_011"
        ],
        [
            "Screenshot (11)",
            "Screenshot (14)",
            "Screenshot (24)",
            "Screenshot (8)",
            "Screenshot (25)",
            "Screenshot (16)",
            "Screenshot (21)",
            "Screenshot (20)",
            "Screenshot (23)",
            "Screenshot (17)",
            "Screenshot (7)",
            "Screenshot (18)",
            "Screenshot (15)",
            "Screenshot (13)",
            "Screenshot (12)",
            "Screenshot (22)",
            "Screenshot (6)",
            "Screenshot (19)",
            "Screenshot (9)"
        ],
        [
            "index102_frame_004",
            "index102_frame_016",
            "index102_frame_006",
            "index102_frame_005",
            "index102_frame_020",
            "index102_frame_012",
            "index108_frame_004",
            "index102_frame_001",
            "index108_frame_016",
            "DataSetVari 46",
            "index108_frame_005",
            "index102_frame_008",
            "index108_frame_019",
            "index108_frame_011",
            "index108_frame_012",
            "index99_frame_008",
            "index99_frame_019",
            "index99_frame_013",
            "index99_frame_012"
        ],
        [
            "index62_frame_025",
            "index62_frame_018",
            "index62_frame_024",
            "index62_frame_006",
            "index62_frame_002",
            "index62_frame_021",
            "index62_frame_017",
            "index62_frame_027",
            "index62_frame_014",
            "index62_frame_013",
            "index62_frame_003",
            "index62_frame_028",
            "index62_frame_016",
            "index62_frame_010",
            "index62_frame_012",
            "index62_frame_011",
            "index62_frame_022",
            "index62_frame_023",
            "index62_frame_030"
        ],
        [
            "index88_frame_024",
            "index88_frame_017",
            "index88_frame_021",
            "index88_frame_008",
            "index88_frame_011",
            "index88_frame_013",
            "index88_frame_010",
            "index88_frame_018",
            "index88_frame_027",
            "index88_frame_012",
            "index88_frame_026",
            "index88_frame_028",
            "index88_frame_030",
            "index88_frame_001",
            "index88_frame_025",
            "index88_frame_022",
            "index88_frame_029",
            "index88_frame_002",
            "index88_frame_014"
        ],
        [
            "index80_frame_004",
            "index2_frame_006",
            "index80_frame_012",
            "index80_frame_017",
            "index2_frame_013",
            "index83_frame_003",
            "index80_frame_013",
            "index83_frame_005",
            "index2_frame_018",
            "index69_frame_008",
            "index69_frame_009",
            "index2_frame_012",
            "index80_frame_003",
            "index83_frame_006",
            "index83_frame_012",
            "index69_frame_007",
            "index69_frame_005",
            "index69_frame_002",
            "index86_frame_067"
        ],
        [
            "index8_frame_023",
            "index8_frame_029",
            "index8_frame_007",
            "index8_frame_027",
            "index8_frame_002",
            "index8_frame_030",
            "index15_frame_011",
            "index15_frame_018",
            "DataSetVari 58",
            "DataSetVari 56",
            "index15_frame_012",
            "index113_frame_008",
            "DataSetVari 54",
            "DataSetVari 48",
            "DataSetVari 66",
            "index113_frame_019",
            "index113_frame_002",
            "DataSetVari 5",
            "index15_frame_027"
        ],
        [
            "index82_frame_023",
            "index82_frame_021",
            "index82_frame_018",
            "index82_frame_015",
            "index82_frame_011",
            "index82_frame_022",
            "index82_frame_026",
            "index82_frame_019",
            "index82_frame_027",
            "index82_frame_010",
            "index82_frame_009",
            "index82_frame_003",
            "index82_frame_024",
            "index82_frame_028",
            "index82_frame_025",
            "index82_frame_020",
            "index82_frame_017",
            "index82_frame_001",
            "index82_frame_029"
        ],
        [
            "Alto 34",
            "DataSetVari 33",
            "Alto 39",
            "Alto 35",
            "DataSetVari 36",
            "Alto 42",
            "DataSetVari 39",
            "DataSetVari 44",
            "Alto 52",
            "DataSetVari 83",
            "DataSetVari 37",
            "index81_frame_002",
            "Alto 46",
            "index81_frame_013",
            "DataSetVari 73",
            "Alto 45",
            "DataSetVari 24",
            "DataSetVari 1",
            "DataSetVari 72"
        ],
        [
            "index20_frame_014",
            "index95_frame_018",
            "index20_frame_009",
            "index95_frame_003",
            "index20_frame_018",
            "index95_frame_014",
            "index95_frame_001",
            "index95_frame_005",
            "index20_frame_005",
            "index33_frame_010",
            "index33_frame_004",
            "index33_frame_011",
            "index33_frame_001",
            "index33_frame_006",
            "index33_frame_009",
            "index20_frame_001",
            "index9_frame_019",
            "index33_frame_002",
            "index9_frame_012"
        ],
        [
            "index31_frame_028",
            "index31_frame_017",
            "index31_frame_021",
            "index31_frame_003",
            "index31_frame_012",
            "index31_frame_001",
            "index31_frame_010",
            "index31_frame_024",
            "index31_frame_005",
            "index31_frame_009",
            "index31_frame_019",
            "index31_frame_007",
            "index31_frame_026",
            "index31_frame_004",
            "index31_frame_022",
            "index31_frame_030",
            "index31_frame_015"
        ],
        [
            "index100_frame_013",
            "index25_frame_004",
            "index100_frame_004",
            "index100_frame_005",
            "index100_frame_006",
            "index18_frame_008",
            "index18_frame_002",
            "index18_frame_004",
            "index100_frame_020",
            "index18_frame_006",
            "index32_frame_017",
            "index26_frame_012",
            "index26_frame_015",
            "index32_frame_011",
            "index26_frame_010",
            "index16_frame_016",
            "Screenshot (573)",
            "index32_frame_019",
            "Screenshot (520)"
        ],
        [
            "index104_frame_015",
            "index104_frame_002",
            "index104_frame_010",
            "Screenshot (625)",
            "index104_frame_001",
            "index104_frame_018",
            "Screenshot (637)",
            "Screenshot (639)",
            "Screenshot (621)",
            "Screenshot (677)",
            "index104_frame_004",
            "index6_frame_020",
            "Screenshot (673)",
            "Screenshot (670)",
            "index6_frame_010",
            "index6_frame_012",
            "index6_frame_002",
            "index6_frame_013",
            "Screenshot (624)"
        ]
    ]
}