{
    "k": 24,
    "inertia_score": -253361.0625,
    "silhouette_score": 0.10697199404239655,
    "cluster_counts": [
        77,
        18,
        131,
        45,
        63,
        34,
        70,
        41,
        116,
        71,
        31,
        108,
        40,
        74,
        48,
        51,
        58,
        138,
        20,
        53,
        61,
        78,
        42,
        30
    ],
    "samples": [
        [
            "Screenshot (57)",
            "Screenshot (52)",
            "Screenshot (63)",
            "index62_frame_012",
            "index62_frame_013",
            "Screenshot (65)",
            "Screenshot (55)",
            "index9_frame_015",
            "index20_frame_018",
            "Screenshot (67)",
            "index33_frame_001",
            "index62_frame_011",
            "index33_frame_016",
            "index9_frame_002",
            "index54_frame_009",
            "index62_frame_018",
            "index54_frame_002",
            "index9_frame_004",
            "index62_frame_005",
            "index19_frame_013",
            "index9_frame_010",
            "index54_frame_004",
            "index7_frame_015",
            "index108_frame_002",
            "index62_frame_015"
        ],
        [
            "index71_frame_009",
            "index71_frame_011",
            "index71_frame_012",
            "index71_frame_004",
            "index71_frame_002",
            "index71_frame_010",
            "index71_frame_008",
            "index71_frame_015",
            "index71_frame_014",
            "index71_frame_007",
            "index71_frame_001",
            "index71_frame_006",
            "index71_frame_013",
            "index71_frame_003",
            "index71_frame_016",
            "index71_frame_017",
            "index71_frame_005",
            "index7_frame_001"
        ],
        [
            "Screenshot (303)",
            "Screenshot (294)",
            "Screenshot (292)",
            "Screenshot (320)",
            "index83_frame_004",
            "index83_frame_012",
            "index90_frame_017",
            "Screenshot (318)",
            "index90_frame_008",
            "index83_frame_009",
            "Screenshot (46)",
            "index2_frame_013",
            "Screenshot (321)",
            "index69_frame_011",
            "index69_frame_009",
            "index90_frame_007",
            "Screenshot (507)",
            "Screenshot (512)",
            "Screenshot (29)",
            "Screenshot (502)",
            "Screenshot (529)",
            "Screenshot (501)",
            "index113_frame_005",
            "Screenshot (519)",
            "Foto 16"
        ],
        [
            "index41_frame_005",
            "index41_frame_001",
            "index41_frame_002",
            "index100_frame_002",
            "index100_frame_006",
            "index100_frame_017",
            "index100_frame_005",
            "index41_frame_008",
            "index100_frame_019",
            "index100_frame_004",
            "index100_frame_009",
            "index100_frame_015",
            "index100_frame_003",
            "index100_frame_010",
            "index100_frame_013",
            "index41_frame_013",
            "index41_frame_016",
            "index41_frame_019",
            "index41_frame_017",
            "index41_frame_018",
            "index100_frame_001",
            "index28_frame_009",
            "index100_frame_020",
            "index28_frame_004",
            "index28_frame_008"
        ],
        [
            "Screenshot (256)",
            "Screenshot (279)",
            "Screenshot (276)",
            "Screenshot (264)",
            "Screenshot (260)",
            "Screenshot (267)",
            "Screenshot (280)",
            "Screenshot (277)",
            "Screenshot (255)",
            "Screenshot (274)",
            "Screenshot (270)",
            "index109_frame_014",
            "index109_frame_018",
            "index109_frame_015",
            "index109_frame_002",
            "index88_frame_013",
            "index109_frame_019",
            "index109_frame_003",
            "Screenshot (359)",
            "Screenshot (361)",
            "index109_frame_007",
            "Screenshot (355)",
            "Screenshot (374)",
            "Screenshot (407)",
            "index109_frame_008"
        ],
        [
            "Screenshot (24)",
            "Screenshot (23)",
            "Screenshot (10)",
            "Screenshot (15)",
            "Screenshot (14)",
            "Screenshot (2)",
            "Screenshot (16)",
            "Screenshot (22)",
            "Screenshot (20)",
            "Screenshot (25)",
            "Screenshot (8)",
            "Screenshot (6)",
            "Screenshot (11)",
            "Screenshot (9)",
            "Screenshot (17)",
            "Screenshot (7)",
            "Screenshot (21)",
            "Screenshot (18)",
            "Screenshot (13)",
            "Screenshot (12)",
            "Screenshot (19)",
            "DataSetVari 32",
            "DataSetVari 44",
            "DataSetVari 45",
            "DataSetVari 35"
        ],
        [
            "Screenshot (422)",
            "Screenshot (426)",
            "Screenshot (425)",
            "Screenshot (411)",
            "Screenshot (414)",
            "Screenshot (480)",
            "Screenshot (466)",
            "Screenshot (469)",
            "Screenshot (476)",
            "Screenshot (408)",
            "Screenshot (416)",
            "Screenshot (420)",
            "Screenshot (417)",
            "Screenshot (421)",
            "Screenshot (455)",
            "Screenshot (447)",
            "Screenshot (461)",
            "DataSetVari 19",
            "DataSetVari 18",
            "Screenshot (445)",
            "DataSetVari 13",
            "DataSetVari 22",
            "index114_frame_009",
            "index106_frame_004",
            "DataSetVari 16"
        ],
        [
            "index80_frame_004",
            "index80_frame_012",
            "index80_frame_009",
            "index2_frame_006",
            "index80_frame_006",
            "index80_frame_017",
            "index80_frame_013",
            "index80_frame_015",
            "index80_frame_007",
            "index80_frame_014",
            "index80_frame_008",
            "index80_frame_018",
            "index80_frame_005",
            "index80_frame_001",
            "index80_frame_011",
            "index80_frame_010",
            "index80_frame_016",
            "index2_frame_004",
            "index80_frame_019",
            "index2_frame_001",
            "index80_frame_002",
            "index80_frame_003",
            "index2_frame_020",
            "index92_frame_018",
            "index92_frame_006"
        ],
        [
            "Foto 202",
            "Foto 149",
            "Foto 27",
            "Foto 204",
            "Foto 216",
            "Foto 104",
            "Foto 93",
            "Foto 108",
            "Foto 64",
            "index94_frame_001",
            "Foto 195",
            "Foto 28",
            "Foto 37",
            "Foto 106",
            "Foto 153",
            "Foto 152",
            "Foto 81",
            "Foto 22",
            "Foto 41",
            "Foto 17",
            "Foto 63",
            "Foto 26",
            "Foto 155",
            "Foto 145",
            "Foto 10"
        ],
        [
            "index104_frame_015",
            "index104_frame_011",
            "index102_frame_006",
            "index104_frame_002",
            "index104_frame_020",
            "index104_frame_010",
            "index104_frame_001",
            "index102_frame_008",
            "index102_frame_019",
            "index102_frame_018",
            "index6_frame_005",
            "index102_frame_007",
            "index6_frame_006",
            "index104_frame_016",
            "index6_frame_003",
            "index104_frame_018",
            "index6_frame_004",
            "index102_frame_005",
            "Screenshot (677)",
            "index102_frame_012",
            "index6_frame_010",
            "Screenshot (637)",
            "Screenshot (639)",
            "Screenshot (665)",
            "Screenshot (641)"
        ],
        [
            "Foto 118",
            "Foto 125",
            "Foto 117",
            "Foto 129",
            "Foto 127",
            "Foto 122",
            "Foto 126",
            "Foto 130",
            "Foto 128",
            "Foto 116",
            "Foto 113",
            "Foto 121",
            "Foto 138",
            "Foto 124",
            "Foto 115",
            "Foto 131",
            "Foto 119",
            "Foto 112",
            "Foto 114",
            "Foto 120",
            "Foto 135",
            "Foto 136",
            "Foto 140",
            "Foto 111",
            "Foto 132"
        ],
        [
            "index67_frame_009",
            "index3_frame_013",
            "index67_frame_006",
            "index90_frame_024",
            "index3_frame_003",
            "index82_frame_007",
            "index3_frame_012",
            "index79_frame_011",
            "index90_frame_029",
            "index3_frame_019",
            "index82_frame_016",
            "index85_frame_004",
            "index90_frame_023",
            "index86_frame_009",
            "index86_frame_015",
            "index85_frame_013",
            "index90_frame_026",
            "index79_frame_014",
            "index46_frame_013",
            "index86_frame_004",
            "index86_frame_007",
            "index86_frame_006",
            "index65_frame_003",
            "index65_frame_013",
            "index65_frame_001"
        ],
        [
            "index57_frame_009",
            "index57_frame_013",
            "index57_frame_007",
            "index57_frame_015",
            "index57_frame_006",
            "index57_frame_020",
            "index57_frame_018",
            "index74_frame_004",
            "index57_frame_004",
            "index74_frame_011",
            "index57_frame_016",
            "index57_frame_012",
            "index74_frame_007",
            "index74_frame_010",
            "index74_frame_018",
            "index57_frame_008",
            "index74_frame_006",
            "index57_frame_017",
            "index74_frame_016",
            "index57_frame_011",
            "index57_frame_010",
            "index57_frame_003",
            "index74_frame_003",
            "index74_frame_012",
            "index74_frame_019"
        ],
        [
            "Screenshot (551)",
            "Screenshot (567)",
            "Screenshot (582)",
            "Screenshot (548)",
            "Screenshot (553)",
            "Screenshot (574)",
            "Screenshot (542)",
            "Screenshot (547)",
            "Screenshot (545)",
            "Screenshot (584)",
            "Foto 177",
            "Screenshot (556)",
            "index4_frame_001",
            "index18_frame_015",
            "Foto 181",
            "index18_frame_010",
            "index18_frame_013",
            "Foto 182",
            "Foto 186",
            "index4_frame_003",
            "Screenshot (590)",
            "Screenshot (576)",
            "DataSetVari 9",
            "Screenshot (571)",
            "Foto 180"
        ],
        [
            "Screenshot (190)",
            "Screenshot (193)",
            "Screenshot (185)",
            "Screenshot (194)",
            "Screenshot (196)",
            "Screenshot (167)",
            "Screenshot (191)",
            "Screenshot (177)",
            "Screenshot (189)",
            "Screenshot (183)",
            "Screenshot (184)",
            "Screenshot (199)",
            "Screenshot (186)",
            "Screenshot (192)",
            "Screenshot (176)",
            "Screenshot (197)",
            "Screenshot (195)",
            "Screenshot (187)",
            "Screenshot (170)",
            "Screenshot (188)",
            "Screenshot (174)",
            "Screenshot (173)",
            "Screenshot (169)",
            "Screenshot (175)",
            "Screenshot (200)"
        ],
        [
            "Alto 69",
            "Alto 74",
            "index106_frame_010",
            "Screenshot (524)",
            "Alto 64",
            "Alto 73",
            "Alto 70",
            "index81_frame_009",
            "Alto 40",
            "index81_frame_013",
            "index81_frame_018",
            "DataSetVari 87",
            "DataSetVari 95",
            "Alto 44",
            "index81_frame_003",
            "DataSetVari 91",
            "Alto 33",
            "DataSetVari 86",
            "Alto 39",
            "DataSetVari 99",
            "Alto 31",
            "DataSetVari 90",
            "DataSetVari 85",
            "DataSetVari 101",
            "Alto 30"
        ],
        [
            "Screenshot (136)",
            "index70_frame_008",
            "index70_frame_003",
            "Screenshot (161)",
            "Screenshot (145)",
            "Screenshot (160)",
            "index70_frame_020",
            "index70_frame_004",
            "index70_frame_016",
            "Screenshot (158)",
            "index70_frame_002",
            "index70_frame_001",
            "Screenshot (157)",
            "index70_frame_019",
            "Screenshot (147)",
            "index70_frame_018",
            "Screenshot (143)",
            "index70_frame_005",
            "index70_frame_006",
            "index70_frame_013",
            "Screenshot (138)",
            "Screenshot (132)",
            "Screenshot (118)",
            "Screenshot (137)",
            "index9_frame_011"
        ],
        [
            "index66_frame_007",
            "index66_frame_011",
            "Screenshot (247)",
            "index66_frame_009",
            "Screenshot (95)",
            "Screenshot (208)",
            "Screenshot (244)",
            "Screenshot (91)",
            "Screenshot (84)",
            "index25_frame_003",
            "index59_frame_009",
            "index38_frame_019",
            "Screenshot (162)",
            "index38_frame_003",
            "Screenshot (232)",
            "index59_frame_007",
            "index38_frame_017",
            "Screenshot (248)",
            "index107_frame_006",
            "DataSetVari 56",
            "Screenshot (100)",
            "index59_frame_010",
            "DataSetVari 66",
            "index26_frame_003",
            "Screenshot (68)"
        ],
        [
            "index72_frame_014",
            "index72_frame_016",
            "index72_frame_017",
            "index72_frame_006",
            "index72_frame_008",
            "index72_frame_015",
            "index72_frame_018",
            "index72_frame_011",
            "index72_frame_019",
            "index72_frame_012",
            "index72_frame_013",
            "index72_frame_005",
            "index72_frame_001",
            "index72_frame_007",
            "index72_frame_003",
            "index72_frame_010",
            "index72_frame_009",
            "index72_frame_004",
            "index72_frame_002",
            "index72_frame_020"
        ],
        [
            "Foto 220",
            "Foto 222",
            "Foto 213",
            "Foto 77",
            "Foto 147",
            "Screenshot (328)",
            "Foto 225",
            "Foto 143",
            "Screenshot (340)",
            "Screenshot (337)",
            "Foto 141",
            "Foto 157",
            "Foto 49",
            "Foto 206",
            "Foto 212",
            "Foto 38",
            "Foto 98",
            "Foto 210",
            "Foto 154",
            "Foto 86",
            "Foto 207",
            "Foto 1",
            "Foto 110",
            "Foto 200",
            "Foto 78"
        ],
        [
            "index20_frame_014",
            "index20_frame_026",
            "index20_frame_010",
            "index20_frame_021",
            "index20_frame_013",
            "index95_frame_005",
            "index95_frame_008",
            "index95_frame_009",
            "index95_frame_012",
            "index14_frame_007",
            "index20_frame_012",
            "index95_frame_011",
            "index95_frame_003",
            "index95_frame_004",
            "index14_frame_017",
            "index95_frame_020",
            "index95_frame_001",
            "index20_frame_011",
            "index20_frame_001",
            "Foto 173",
            "index108_frame_014",
            "Foto 175",
            "index20_frame_002",
            "index14_frame_006",
            "index20_frame_007"
        ],
        [
            "index23_frame_009",
            "Alto 78",
            "index23_frame_006",
            "Alto 80",
            "index23_frame_007",
            "Alto 9",
            "index23_frame_012",
            "DataSetVari 41",
            "Alto 79",
            "DataSetVari 33",
            "DataSetVari 34",
            "index23_frame_016",
            "Alto 85",
            "Alto 4",
            "Alto 38",
            "Alto 86",
            "Alto 2",
            "DataSetVari 29",
            "DataSetVari 4",
            "DataSetVari 74",
            "DataSetVari 31",
            "DataSetVari 77",
            "DataSetVari 70",
            "DataSetVari 73",
            "DataSetVari 81"
        ],
        [
            "index32_frame_008",
            "index32_frame_007",
            "index32_frame_017",
            "index32_frame_006",
            "index32_frame_009",
            "index32_frame_018",
            "index32_frame_003",
            "index32_frame_011",
            "index32_frame_015",
            "index108_frame_016",
            "index32_frame_010",
            "index32_frame_001",
            "DataSetVari 46",
            "index32_frame_004",
            "index32_frame_019",
            "index108_frame_005",
            "index32_frame_002",
            "index32_frame_014",
            "index108_frame_008",
            "index32_frame_016",
            "index32_frame_013",
            "index32_frame_020",
            "index32_frame_005",
            "index108_frame_011",
            "index108_frame_009"
        ],
        [
            "Alto 57",
            "Alto 60",
            "Alto 61",
            "Alto 56",
            "Alto 5",
            "Alto 62",
            "Alto 19",
            "Alto 6",
            "Alto 14",
            "Alto 18",
            "Alto 58",
            "Alto 7",
            "Alto 15",
            "Alto 55",
            "Alto 59",
            "Alto 45",
            "Alto 12",
            "Alto 49",
            "DataSetVari 1",
            "index114_frame_013",
            "Alto 54",
            "DataSetVari 12",
            "DataSetVari 6",
            "Alto 22",
            "Alto 21"
        ]
    ]
}